<?xml version="1.0" encoding="ISO-8859-9"?> <Events org="tffbirincilig"><Event eventtypeID="1" orgID="4" week="1" matchID="106971" hometeamID="130" awayteamID="58" placeID="36" eventdate="09.09.2012" eventtime="16:00"/><Event eventtypeID="1" orgID="4" week="1" matchID="106972" hometeamID="121" awayteamID="114" placeID="334" eventdate="09.09.2012" eventtime="16:00"/><Event eventtypeID="1" orgID="4" week="1" matchID="106973" hometeamID="91" awayteamID="3696" placeID="33" eventdate="09.09.2012" eventtime="16:00"/><Event eventtypeID="1" orgID="4" week="1" matchID="106974" hometeamID="3623" awayteamID="379" placeID="104" eventdate="09.09.2012" eventtime="16:00"/><Event eventtypeID="1" orgID="4" week="1" matchID="106975" hometeamID="30" awayteamID="3637" placeID="143" eventdate="09.09.2012" eventtime="16:00"/><Event eventtypeID="1" orgID="4" week="1" matchID="106976" hometeamID="3594" awayteamID="4366" placeID="159" eventdate="09.09.2012" eventtime="16:00"/><Event eventtypeID="1" orgID="4" week="1" matchID="106977" hometeamID="3629" awayteamID="129" placeID="74" eventdate="09.09.2012" eventtime="16:00"/><Event eventtypeID="1" orgID="4" week="1" matchID="106970" hometeamID="3639" awayteamID="3618" placeID="39" eventdate="09.09.2012" eventtime="17:00"/><Event eventtypeID="1" orgID="4" week="2" matchID="106978" hometeamID="3618" awayteamID="130" placeID="95" eventdate="16.09.2012" eventtime="16:00"/><Event eventtypeID="1" orgID="4" week="2" matchID="106979" hometeamID="129" awayteamID="3602" placeID="82" eventdate="16.09.2012" eventtime="16:00"/><Event eventtypeID="1" orgID="4" week="2" matchID="106980" hometeamID="4366" awayteamID="3629" placeID="20" eventdate="16.09.2012" eventtime="16:00"/><Event eventtypeID="1" orgID="4" week="2" matchID="106981" hometeamID="3637" awayteamID="3594" placeID="154" eventdate="16.09.2012" eventtime="16:00"/><Event eventtypeID="1" orgID="4" week="2" matchID="106982" hometeamID="379" awayteamID="30" placeID="53" eventdate="16.09.2012" eventtime="16:00"/><Event eventtypeID="1" orgID="4" week="2" matchID="106984" hometeamID="114" awayteamID="91" placeID="476" eventdate="16.09.2012" eventtime="16:00"/><Event eventtypeID="1" orgID="4" week="2" matchID="106985" hometeamID="58" awayteamID="121" placeID="148" eventdate="16.09.2012" eventtime="19:00"/><Event eventtypeID="1" orgID="4" week="2" matchID="106983" hometeamID="3696" awayteamID="3623" placeID="5372" eventdate="17.09.2012" eventtime="16:00"/><Event eventtypeID="1" orgID="4" week="3" matchID="106987" hometeamID="121" awayteamID="3618" placeID="334" eventdate="22.09.2012" eventtime="15:00"/><Event eventtypeID="1" orgID="4" week="3" matchID="106988" hometeamID="91" awayteamID="58" placeID="33" eventdate="23.09.2012" eventtime="15:00"/><Event eventtypeID="1" orgID="4" week="3" matchID="106989" hometeamID="3623" awayteamID="114" placeID="104" eventdate="23.09.2012" eventtime="15:00"/><Event eventtypeID="1" orgID="4" week="3" matchID="106990" hometeamID="30" awayteamID="3696" placeID="143" eventdate="23.09.2012" eventtime="15:00"/><Event eventtypeID="1" orgID="4" week="3" matchID="106991" hometeamID="3594" awayteamID="379" placeID="159" eventdate="23.09.2012" eventtime="15:00"/><Event eventtypeID="1" orgID="4" week="3" matchID="106986" hometeamID="130" awayteamID="3639" placeID="36" eventdate="23.09.2012" eventtime="15:00"/><Event eventtypeID="1" orgID="4" week="3" matchID="106993" hometeamID="3602" awayteamID="4366" placeID="96" eventdate="23.09.2012" eventtime="15:00"/><Event eventtypeID="1" orgID="4" week="3" matchID="106992" hometeamID="3629" awayteamID="3637" placeID="74" eventdate="23.09.2012" eventtime="19:00"/><Event eventtypeID="1" orgID="4" week="4" matchID="106994" hometeamID="3618" awayteamID="91" placeID="95" eventdate="30.09.2012" eventtime="15:00"/><Event eventtypeID="1" orgID="4" week="4" matchID="106995" hometeamID="3639" awayteamID="121" placeID="39" eventdate="30.09.2012" eventtime="15:00"/><Event eventtypeID="1" orgID="4" week="4" matchID="106996" hometeamID="4366" awayteamID="129" placeID="19" eventdate="30.09.2012" eventtime="15:00"/><Event eventtypeID="1" orgID="4" week="4" matchID="106997" hometeamID="3637" awayteamID="3602" placeID="154" eventdate="30.09.2012" eventtime="15:00"/><Event eventtypeID="1" orgID="4" week="4" matchID="106998" hometeamID="379" awayteamID="3629" placeID="53" eventdate="30.09.2012" eventtime="15:00"/><Event eventtypeID="1" orgID="4" week="4" matchID="106999" hometeamID="3696" awayteamID="3594" placeID="5372" eventdate="30.09.2012" eventtime="15:00"/><Event eventtypeID="1" orgID="4" week="4" matchID="107000" hometeamID="114" awayteamID="30" placeID="476" eventdate="30.09.2012" eventtime="15:00"/><Event eventtypeID="1" orgID="4" week="4" matchID="107001" hometeamID="58" awayteamID="3623" placeID="148" eventdate="30.09.2012" eventtime="19:00"/><Event eventtypeID="1" orgID="4" week="5" matchID="107002" hometeamID="121" awayteamID="130" placeID="334" eventdate="06.10.2012" eventtime="15:00"/><Event eventtypeID="1" orgID="4" week="5" matchID="107003" hometeamID="91" awayteamID="3639" placeID="33" eventdate="07.10.2012" eventtime="15:00"/><Event eventtypeID="1" orgID="4" week="5" matchID="107004" hometeamID="3623" awayteamID="3618" placeID="104" eventdate="07.10.2012" eventtime="15:00"/><Event eventtypeID="1" orgID="4" week="5" matchID="107005" hometeamID="30" awayteamID="58" placeID="143" eventdate="07.10.2012" eventtime="15:00"/><Event eventtypeID="1" orgID="4" week="5" matchID="107006" hometeamID="3594" awayteamID="114" placeID="159" eventdate="07.10.2012" eventtime="15:00"/><Event eventtypeID="1" orgID="4" week="5" matchID="107007" hometeamID="3629" awayteamID="3696" placeID="74" eventdate="07.10.2012" eventtime="15:00"/><Event eventtypeID="1" orgID="4" week="5" matchID="107008" hometeamID="3602" awayteamID="379" placeID="96" eventdate="07.10.2012" eventtime="15:00"/><Event eventtypeID="1" orgID="4" week="5" matchID="107009" hometeamID="129" awayteamID="3637" placeID="82" eventdate="07.10.2012" eventtime="15:00"/><Event eventtypeID="1" orgID="4" week="6" matchID="107010" hometeamID="3618" awayteamID="30" placeID="95" eventdate="14.10.2012" eventtime="15:00"/><Event eventtypeID="1" orgID="4" week="6" matchID="107011" hometeamID="3639" awayteamID="3623" placeID="39" eventdate="14.10.2012" eventtime="15:00"/><Event eventtypeID="1" orgID="4" week="6" matchID="107012" hometeamID="130" awayteamID="91" placeID="36" eventdate="14.10.2012" eventtime="15:00"/><Event eventtypeID="1" orgID="4" week="6" matchID="107013" hometeamID="3637" awayteamID="4366" placeID="154" eventdate="14.10.2012" eventtime="15:00"/><Event eventtypeID="1" orgID="4" week="6" matchID="107014" hometeamID="379" awayteamID="129" placeID="53" eventdate="14.10.2012" eventtime="15:00"/><Event eventtypeID="1" orgID="4" week="6" matchID="107015" hometeamID="3696" awayteamID="3602" placeID="5372" eventdate="14.10.2012" eventtime="15:00"/><Event eventtypeID="1" orgID="4" week="6" matchID="107016" hometeamID="114" awayteamID="3629" placeID="476" eventdate="14.10.2012" eventtime="15:00"/><Event eventtypeID="1" orgID="4" week="6" matchID="107017" hometeamID="58" awayteamID="3594" placeID="148" eventdate="14.10.2012" eventtime="15:00"/><Event eventtypeID="1" orgID="4" week="7" matchID="107018" hometeamID="91" awayteamID="121" placeID="33" eventdate="21.10.2012" eventtime="15:00"/><Event eventtypeID="1" orgID="4" week="7" matchID="107019" hometeamID="3623" awayteamID="130" placeID="104" eventdate="21.10.2012" eventtime="15:00"/><Event eventtypeID="1" orgID="4" week="7" matchID="107020" hometeamID="30" awayteamID="3639" placeID="143" eventdate="21.10.2012" eventtime="15:00"/><Event eventtypeID="1" orgID="4" week="7" matchID="107021" hometeamID="3594" awayteamID="3618" placeID="159" eventdate="21.10.2012" eventtime="15:00"/><Event eventtypeID="1" orgID="4" week="7" matchID="107022" hometeamID="3629" awayteamID="58" placeID="74" eventdate="21.10.2012" eventtime="15:00"/><Event eventtypeID="1" orgID="4" week="7" matchID="107023" hometeamID="3602" awayteamID="114" placeID="96" eventdate="21.10.2012" eventtime="15:00"/><Event eventtypeID="1" orgID="4" week="7" matchID="107024" hometeamID="129" awayteamID="3696" placeID="82" eventdate="21.10.2012" eventtime="15:00"/><Event eventtypeID="1" orgID="4" week="7" matchID="107025" hometeamID="4366" awayteamID="379" placeID="19" eventdate="21.10.2012" eventtime="15:00"/><Event eventtypeID="1" orgID="4" week="8" matchID="107031" hometeamID="3696" awayteamID="4366" placeID="5372" eventdate="27.10.2012" eventtime="13:30"/><Event eventtypeID="1" orgID="4" week="8" matchID="107032" hometeamID="114" awayteamID="129" placeID="476" eventdate="28.10.2012" eventtime="13:30"/><Event eventtypeID="1" orgID="4" week="8" matchID="107033" hometeamID="58" awayteamID="3602" placeID="149" eventdate="28.10.2012" eventtime="13:30"/><Event eventtypeID="1" orgID="4" week="8" matchID="107026" hometeamID="3618" awayteamID="3629" placeID="95" eventdate="28.10.2012" eventtime="13:30"/><Event eventtypeID="1" orgID="4" week="8" matchID="107027" hometeamID="3639" awayteamID="3594" placeID="39" eventdate="28.10.2012" eventtime="13:30"/><Event eventtypeID="1" orgID="4" week="8" matchID="107028" hometeamID="130" awayteamID="30" placeID="36" eventdate="28.10.2012" eventtime="13:30"/><Event eventtypeID="1" orgID="4" week="8" matchID="107029" hometeamID="121" awayteamID="3623" placeID="430" eventdate="28.10.2012" eventtime="13:30"/><Event eventtypeID="1" orgID="4" week="8" matchID="107030" hometeamID="379" awayteamID="3637" placeID="53" eventdate="28.10.2012" eventtime="13:30"/><Event eventtypeID="1" orgID="4" week="9" matchID="107034" hometeamID="3623" awayteamID="91" placeID="104" eventdate="04.11.2012" eventtime="13:30"/><Event eventtypeID="1" orgID="4" week="9" matchID="107035" hometeamID="30" awayteamID="121" placeID="143" eventdate="04.11.2012" eventtime="13:30"/><Event eventtypeID="1" orgID="4" week="9" matchID="107036" hometeamID="3594" awayteamID="130" placeID="159" eventdate="04.11.2012" eventtime="13:30"/><Event eventtypeID="1" orgID="4" week="9" matchID="107037" hometeamID="3629" awayteamID="3639" placeID="74" eventdate="04.11.2012" eventtime="13:30"/><Event eventtypeID="1" orgID="4" week="9" matchID="107038" hometeamID="3602" awayteamID="3618" placeID="96" eventdate="04.11.2012" eventtime="13:30"/><Event eventtypeID="1" orgID="4" week="9" matchID="107039" hometeamID="129" awayteamID="58" placeID="82" eventdate="04.11.2012" eventtime="13:30"/><Event eventtypeID="1" orgID="4" week="9" matchID="107040" hometeamID="4366" awayteamID="114" placeID="19" eventdate="04.11.2012" eventtime="13:30"/><Event eventtypeID="1" orgID="4" week="9" matchID="107041" hometeamID="3637" awayteamID="3696" placeID="154" eventdate="04.11.2012" eventtime="13:30"/><Event eventtypeID="1" orgID="4" week="10" matchID="107042" hometeamID="3618" awayteamID="129" placeID="95" eventdate="11.11.2012" eventtime="13:30"/><Event eventtypeID="1" orgID="4" week="10" matchID="107043" hometeamID="3639" awayteamID="3602" placeID="39" eventdate="11.11.2012" eventtime="13:30"/><Event eventtypeID="1" orgID="4" week="10" matchID="107044" hometeamID="130" awayteamID="3629" placeID="36" eventdate="11.11.2012" eventtime="13:30"/><Event eventtypeID="1" orgID="4" week="10" matchID="107045" hometeamID="121" awayteamID="3594" placeID="430" eventdate="11.11.2012" eventtime="13:30"/><Event eventtypeID="1" orgID="4" week="10" matchID="107046" hometeamID="91" awayteamID="30" placeID="33" eventdate="11.11.2012" eventtime="13:30"/><Event eventtypeID="1" orgID="4" week="10" matchID="107047" hometeamID="3696" awayteamID="379" placeID="5372" eventdate="11.11.2012" eventtime="13:30"/><Event eventtypeID="1" orgID="4" week="10" matchID="107048" hometeamID="114" awayteamID="3637" placeID="476" eventdate="11.11.2012" eventtime="13:30"/><Event eventtypeID="1" orgID="4" week="10" matchID="107049" hometeamID="58" awayteamID="4366" placeID="148" eventdate="11.11.2012" eventtime="13:30"/><Event eventtypeID="1" orgID="4" week="11" matchID="107050" hometeamID="30" awayteamID="3623" placeID="143" eventdate="14.11.2012" eventtime="13:30"/><Event eventtypeID="1" orgID="4" week="11" matchID="107051" hometeamID="3594" awayteamID="91" placeID="159" eventdate="14.11.2012" eventtime="13:30"/><Event eventtypeID="1" orgID="4" week="11" matchID="107052" hometeamID="3629" awayteamID="121" placeID="74" eventdate="14.11.2012" eventtime="13:30"/><Event eventtypeID="1" orgID="4" week="11" matchID="107053" hometeamID="3602" awayteamID="130" placeID="96" eventdate="14.11.2012" eventtime="13:30"/><Event eventtypeID="1" orgID="4" week="11" matchID="107054" hometeamID="129" awayteamID="3639" placeID="82" eventdate="14.11.2012" eventtime="13:30"/><Event eventtypeID="1" orgID="4" week="11" matchID="107055" hometeamID="4366" awayteamID="3618" placeID="19" eventdate="14.11.2012" eventtime="13:30"/><Event eventtypeID="1" orgID="4" week="11" matchID="107056" hometeamID="3637" awayteamID="58" placeID="154" eventdate="14.11.2012" eventtime="13:30"/><Event eventtypeID="1" orgID="4" week="11" matchID="107057" hometeamID="379" awayteamID="114" placeID="53" eventdate="14.11.2012" eventtime="13:30"/><Event eventtypeID="1" orgID="4" week="12" matchID="107058" hometeamID="3618" awayteamID="3637" placeID="95" eventdate="18.11.2012" eventtime="13:30"/><Event eventtypeID="1" orgID="4" week="12" matchID="107059" hometeamID="3639" awayteamID="4366" placeID="39" eventdate="18.11.2012" eventtime="13:30"/><Event eventtypeID="1" orgID="4" week="12" matchID="107060" hometeamID="130" awayteamID="129" placeID="36" eventdate="18.11.2012" eventtime="13:30"/><Event eventtypeID="1" orgID="4" week="12" matchID="107061" hometeamID="121" awayteamID="3602" placeID="430" eventdate="18.11.2012" eventtime="13:30"/><Event eventtypeID="1" orgID="4" week="12" matchID="107062" hometeamID="91" awayteamID="3629" placeID="33" eventdate="18.11.2012" eventtime="13:30"/><Event eventtypeID="1" orgID="4" week="12" matchID="107063" hometeamID="3623" awayteamID="3594" placeID="104" eventdate="18.11.2012" eventtime="13:30"/><Event eventtypeID="1" orgID="4" week="12" matchID="107064" hometeamID="114" awayteamID="3696" placeID="476" eventdate="18.11.2012" eventtime="13:30"/><Event eventtypeID="1" orgID="4" week="12" matchID="107065" hometeamID="58" awayteamID="379" placeID="148" eventdate="18.11.2012" eventtime="13:30"/><Event eventtypeID="1" orgID="4" week="13" matchID="107070" hometeamID="4366" awayteamID="130" placeID="19" eventdate="24.11.2012" eventtime="13:30"/><Event eventtypeID="1" orgID="4" week="13" matchID="107071" hometeamID="3637" awayteamID="3639" placeID="154" eventdate="24.11.2012" eventtime="13:30"/><Event eventtypeID="1" orgID="4" week="13" matchID="107067" hometeamID="3629" awayteamID="3623" placeID="74" eventdate="24.11.2012" eventtime="13:30"/><Event eventtypeID="1" orgID="4" week="13" matchID="107068" hometeamID="3602" awayteamID="91" placeID="96" eventdate="24.11.2012" eventtime="13:30"/><Event eventtypeID="1" orgID="4" week="13" matchID="107069" hometeamID="129" awayteamID="121" placeID="82" eventdate="25.11.2012" eventtime="13:30"/><Event eventtypeID="1" orgID="4" week="13" matchID="107066" hometeamID="3594" awayteamID="30" placeID="159" eventdate="25.11.2012" eventtime="13:30"/><Event eventtypeID="1" orgID="4" week="13" matchID="107072" hometeamID="379" awayteamID="3618" placeID="53" eventdate="25.11.2012" eventtime="13:30"/><Event eventtypeID="1" orgID="4" week="13" matchID="107073" hometeamID="3696" awayteamID="58" placeID="5372" eventdate="25.11.2012" eventtime="13:30"/><Event eventtypeID="1" orgID="4" week="14" matchID="107078" hometeamID="91" awayteamID="129" placeID="33" eventdate="01.12.2012" eventtime="13:30"/><Event eventtypeID="1" orgID="4" week="14" matchID="107075" hometeamID="3639" awayteamID="379" placeID="39" eventdate="01.12.2012" eventtime="13:30"/><Event eventtypeID="1" orgID="4" week="14" matchID="107076" hometeamID="130" awayteamID="3637" placeID="36" eventdate="02.12.2012" eventtime="13:30"/><Event eventtypeID="1" orgID="4" week="14" matchID="107077" hometeamID="121" awayteamID="4366" placeID="430" eventdate="02.12.2012" eventtime="13:30"/><Event eventtypeID="1" orgID="4" week="14" matchID="107074" hometeamID="3618" awayteamID="3696" placeID="95" eventdate="02.12.2012" eventtime="13:30"/><Event eventtypeID="1" orgID="4" week="14" matchID="107079" hometeamID="3623" awayteamID="3602" placeID="104" eventdate="02.12.2012" eventtime="13:30"/><Event eventtypeID="1" orgID="4" week="14" matchID="107080" hometeamID="30" awayteamID="3629" placeID="143" eventdate="02.12.2012" eventtime="13:30"/><Event eventtypeID="1" orgID="4" week="14" matchID="107081" hometeamID="58" awayteamID="114" placeID="148" eventdate="02.12.2012" eventtime="13:30"/><Event eventtypeID="1" orgID="4" week="15" matchID="107082" hometeamID="3629" awayteamID="3594" placeID="74" eventdate="09.12.2012" eventtime="13:30"/><Event eventtypeID="1" orgID="4" week="15" matchID="107083" hometeamID="3602" awayteamID="30" placeID="96" eventdate="09.12.2012" eventtime="13:30"/><Event eventtypeID="1" orgID="4" week="15" matchID="107084" hometeamID="129" awayteamID="3623" placeID="82" eventdate="09.12.2012" eventtime="13:30"/><Event eventtypeID="1" orgID="4" week="15" matchID="107085" hometeamID="4366" awayteamID="91" placeID="19" eventdate="09.12.2012" eventtime="13:30"/><Event eventtypeID="1" orgID="4" week="15" matchID="107086" hometeamID="3637" awayteamID="121" placeID="154" eventdate="09.12.2012" eventtime="13:30"/><Event eventtypeID="1" orgID="4" week="15" matchID="107087" hometeamID="379" awayteamID="130" placeID="53" eventdate="09.12.2012" eventtime="13:30"/><Event eventtypeID="1" orgID="4" week="15" matchID="107088" hometeamID="3696" awayteamID="3639" placeID="5372" eventdate="09.12.2012" eventtime="13:30"/><Event eventtypeID="1" orgID="4" week="15" matchID="107089" hometeamID="114" awayteamID="3618" placeID="476" eventdate="09.12.2012" eventtime="13:30"/><Event eventtypeID="1" orgID="4" week="16" matchID="107090" hometeamID="3618" awayteamID="58" placeID="95" eventdate="16.12.2012" eventtime="13:30"/><Event eventtypeID="1" orgID="4" week="16" matchID="107091" hometeamID="3639" awayteamID="114" placeID="39" eventdate="16.12.2012" eventtime="13:30"/><Event eventtypeID="1" orgID="4" week="16" matchID="107092" hometeamID="130" awayteamID="3696" placeID="36" eventdate="16.12.2012" eventtime="13:30"/><Event eventtypeID="1" orgID="4" week="16" matchID="107093" hometeamID="121" awayteamID="379" placeID="430" eventdate="16.12.2012" eventtime="13:30"/><Event eventtypeID="1" orgID="4" week="16" matchID="107094" hometeamID="91" awayteamID="3637" placeID="33" eventdate="16.12.2012" eventtime="13:30"/><Event eventtypeID="1" orgID="4" week="16" matchID="107095" hometeamID="3623" awayteamID="4366" placeID="104" eventdate="16.12.2012" eventtime="13:30"/><Event eventtypeID="1" orgID="4" week="16" matchID="107096" hometeamID="30" awayteamID="129" placeID="143" eventdate="16.12.2012" eventtime="13:30"/><Event eventtypeID="1" orgID="4" week="16" matchID="107097" hometeamID="3594" awayteamID="3602" placeID="159" eventdate="16.12.2012" eventtime="13:30"/><Event eventtypeID="1" orgID="4" week="17" matchID="107098" hometeamID="3602" awayteamID="3629" placeID="96" eventdate="23.12.2012" eventtime="13:30"/><Event eventtypeID="1" orgID="4" week="17" matchID="107099" hometeamID="129" awayteamID="3594" placeID="82" eventdate="23.12.2012" eventtime="13:30"/><Event eventtypeID="1" orgID="4" week="17" matchID="107100" hometeamID="4366" awayteamID="30" placeID="19" eventdate="23.12.2012" eventtime="13:30"/><Event eventtypeID="1" orgID="4" week="17" matchID="107101" hometeamID="3637" awayteamID="3623" placeID="154" eventdate="23.12.2012" eventtime="13:30"/><Event eventtypeID="1" orgID="4" week="17" matchID="107102" hometeamID="379" awayteamID="91" placeID="53" eventdate="23.12.2012" eventtime="13:30"/><Event eventtypeID="1" orgID="4" week="17" matchID="107103" hometeamID="3696" awayteamID="121" placeID="5372" eventdate="23.12.2012" eventtime="13:30"/><Event eventtypeID="1" orgID="4" week="17" matchID="107104" hometeamID="114" awayteamID="130" placeID="476" eventdate="23.12.2012" eventtime="13:30"/><Event eventtypeID="1" orgID="4" week="17" matchID="107105" hometeamID="58" awayteamID="3639" placeID="148" eventdate="23.12.2012" eventtime="13:30"/><Event eventtypeID="1" orgID="4" week="18" matchID="107106" hometeamID="3618" awayteamID="3639" placeID="95" eventdate="27.01.2013" eventtime="13:30"/><Event eventtypeID="1" orgID="4" week="18" matchID="107107" hometeamID="58" awayteamID="130" placeID="148" eventdate="27.01.2013" eventtime="13:30"/><Event eventtypeID="1" orgID="4" week="18" matchID="107108" hometeamID="114" awayteamID="121" placeID="476" eventdate="27.01.2013" eventtime="13:30"/><Event eventtypeID="1" orgID="4" week="18" matchID="107109" hometeamID="3696" awayteamID="91" placeID="5372" eventdate="27.01.2013" eventtime="13:30"/><Event eventtypeID="1" orgID="4" week="18" matchID="107110" hometeamID="379" awayteamID="3623" placeID="53" eventdate="27.01.2013" eventtime="13:30"/><Event eventtypeID="1" orgID="4" week="18" matchID="107111" hometeamID="3637" awayteamID="30" placeID="154" eventdate="27.01.2013" eventtime="13:30"/><Event eventtypeID="1" orgID="4" week="18" matchID="107112" hometeamID="4366" awayteamID="3594" placeID="19" eventdate="27.01.2013" eventtime="13:30"/><Event eventtypeID="1" orgID="4" week="18" matchID="107113" hometeamID="129" awayteamID="3629" placeID="82" eventdate="27.01.2013" eventtime="13:30"/><Event eventtypeID="1" orgID="4" week="19" matchID="107114" hometeamID="130" awayteamID="3618" placeID="36" eventdate="03.02.2013" eventtime="13:30"/><Event eventtypeID="1" orgID="4" week="19" matchID="107115" hometeamID="3602" awayteamID="129" placeID="96" eventdate="03.02.2013" eventtime="13:30"/><Event eventtypeID="1" orgID="4" week="19" matchID="107116" hometeamID="3629" awayteamID="4366" placeID="74" eventdate="03.02.2013" eventtime="13:30"/><Event eventtypeID="1" orgID="4" week="19" matchID="107117" hometeamID="3594" awayteamID="3637" placeID="159" eventdate="03.02.2013" eventtime="13:30"/><Event eventtypeID="1" orgID="4" week="19" matchID="107118" hometeamID="30" awayteamID="379" placeID="143" eventdate="03.02.2013" eventtime="13:30"/><Event eventtypeID="1" orgID="4" week="19" matchID="107119" hometeamID="3623" awayteamID="3696" placeID="104" eventdate="03.02.2013" eventtime="13:30"/><Event eventtypeID="1" orgID="4" week="19" matchID="107120" hometeamID="91" awayteamID="114" placeID="33" eventdate="03.02.2013" eventtime="13:30"/><Event eventtypeID="1" orgID="4" week="19" matchID="107121" hometeamID="121" awayteamID="58" placeID="3763" eventdate="03.02.2013" eventtime="13:30"/><Event eventtypeID="1" orgID="4" week="20" matchID="107122" hometeamID="3639" awayteamID="130" placeID="39" eventdate="10.02.2013" eventtime="13:30"/><Event eventtypeID="1" orgID="4" week="20" matchID="107123" hometeamID="3618" awayteamID="121" placeID="95" eventdate="10.02.2013" eventtime="13:30"/><Event eventtypeID="1" orgID="4" week="20" matchID="107124" hometeamID="58" awayteamID="91" placeID="148" eventdate="10.02.2013" eventtime="13:30"/><Event eventtypeID="1" orgID="4" week="20" matchID="107125" hometeamID="114" awayteamID="3623" placeID="476" eventdate="10.02.2013" eventtime="13:30"/><Event eventtypeID="1" orgID="4" week="20" matchID="107126" hometeamID="3696" awayteamID="30" placeID="5372" eventdate="10.02.2013" eventtime="13:30"/><Event eventtypeID="1" orgID="4" week="20" matchID="107127" hometeamID="379" awayteamID="3594" placeID="53" eventdate="10.02.2013" eventtime="13:30"/><Event eventtypeID="1" orgID="4" week="20" matchID="107128" hometeamID="3637" awayteamID="3629" placeID="154" eventdate="10.02.2013" eventtime="13:30"/><Event eventtypeID="1" orgID="4" week="20" matchID="107129" hometeamID="4366" awayteamID="3602" placeID="19" eventdate="10.02.2013" eventtime="13:30"/><Event eventtypeID="1" orgID="4" week="21" matchID="107130" hometeamID="91" awayteamID="3618" placeID="33" eventdate="17.02.2013" eventtime="13:30"/><Event eventtypeID="1" orgID="4" week="21" matchID="107131" hometeamID="121" awayteamID="3639" placeID="3763" eventdate="17.02.2013" eventtime="13:30"/><Event eventtypeID="1" orgID="4" week="21" matchID="107132" hometeamID="129" awayteamID="4366" placeID="82" eventdate="17.02.2013" eventtime="13:30"/><Event eventtypeID="1" orgID="4" week="21" matchID="107133" hometeamID="3602" awayteamID="3637" placeID="96" eventdate="17.02.2013" eventtime="13:30"/><Event eventtypeID="1" orgID="4" week="21" matchID="107134" hometeamID="3629" awayteamID="379" placeID="74" eventdate="17.02.2013" eventtime="13:30"/><Event eventtypeID="1" orgID="4" week="21" matchID="107135" hometeamID="3594" awayteamID="3696" placeID="159" eventdate="17.02.2013" eventtime="13:30"/><Event eventtypeID="1" orgID="4" week="21" matchID="107136" hometeamID="30" awayteamID="114" placeID="143" eventdate="17.02.2013" eventtime="13:30"/><Event eventtypeID="1" orgID="4" week="21" matchID="107137" hometeamID="3623" awayteamID="58" placeID="104" eventdate="17.02.2013" eventtime="13:30"/><Event eventtypeID="1" orgID="4" week="22" matchID="107138" hometeamID="130" awayteamID="121" placeID="36" eventdate="24.02.2013" eventtime="13:30"/><Event eventtypeID="1" orgID="4" week="22" matchID="107139" hometeamID="3639" awayteamID="91" placeID="39" eventdate="24.02.2013" eventtime="13:30"/><Event eventtypeID="1" orgID="4" week="22" matchID="107140" hometeamID="3618" awayteamID="3623" placeID="95" eventdate="24.02.2013" eventtime="13:30"/><Event eventtypeID="1" orgID="4" week="22" matchID="107141" hometeamID="58" awayteamID="30" placeID="148" eventdate="24.02.2013" eventtime="13:30"/><Event eventtypeID="1" orgID="4" week="22" matchID="107142" hometeamID="114" awayteamID="3594" placeID="476" eventdate="24.02.2013" eventtime="13:30"/><Event eventtypeID="1" orgID="4" week="22" matchID="107143" hometeamID="3696" awayteamID="3629" placeID="5372" eventdate="24.02.2013" eventtime="13:30"/><Event eventtypeID="1" orgID="4" week="22" matchID="107144" hometeamID="379" awayteamID="3602" placeID="53" eventdate="24.02.2013" eventtime="13:30"/><Event eventtypeID="1" orgID="4" week="22" matchID="107145" hometeamID="3637" awayteamID="129" placeID="154" eventdate="24.02.2013" eventtime="13:30"/><Event eventtypeID="1" orgID="4" week="23" matchID="107146" hometeamID="30" awayteamID="3618" placeID="143" eventdate="03.03.2013" eventtime="13:30"/><Event eventtypeID="1" orgID="4" week="23" matchID="107147" hometeamID="3623" awayteamID="3639" placeID="104" eventdate="03.03.2013" eventtime="13:30"/><Event eventtypeID="1" orgID="4" week="23" matchID="107148" hometeamID="91" awayteamID="130" placeID="33" eventdate="03.03.2013" eventtime="13:30"/><Event eventtypeID="1" orgID="4" week="23" matchID="107149" hometeamID="4366" awayteamID="3637" placeID="20" eventdate="03.03.2013" eventtime="13:30"/><Event eventtypeID="1" orgID="4" week="23" matchID="107150" hometeamID="129" awayteamID="379" placeID="82" eventdate="03.03.2013" eventtime="13:30"/><Event eventtypeID="1" orgID="4" week="23" matchID="107151" hometeamID="3602" awayteamID="3696" placeID="96" eventdate="03.03.2013" eventtime="13:30"/><Event eventtypeID="1" orgID="4" week="23" matchID="107152" hometeamID="3629" awayteamID="114" placeID="74" eventdate="03.03.2013" eventtime="13:30"/><Event eventtypeID="1" orgID="4" week="23" matchID="107153" hometeamID="3594" awayteamID="58" placeID="159" eventdate="03.03.2013" eventtime="13:30"/><Event eventtypeID="1" orgID="4" week="24" matchID="107154" hometeamID="121" awayteamID="91" placeID="3763" eventdate="10.03.2013" eventtime="13:30"/><Event eventtypeID="1" orgID="4" week="24" matchID="107155" hometeamID="130" awayteamID="3623" placeID="36" eventdate="10.03.2013" eventtime="13:30"/><Event eventtypeID="1" orgID="4" week="24" matchID="107156" hometeamID="3639" awayteamID="30" placeID="39" eventdate="10.03.2013" eventtime="13:30"/><Event eventtypeID="1" orgID="4" week="24" matchID="107157" hometeamID="3618" awayteamID="3594" placeID="95" eventdate="10.03.2013" eventtime="13:30"/><Event eventtypeID="1" orgID="4" week="24" matchID="107158" hometeamID="58" awayteamID="3629" placeID="148" eventdate="10.03.2013" eventtime="13:30"/><Event eventtypeID="1" orgID="4" week="24" matchID="107159" hometeamID="114" awayteamID="3602" placeID="476" eventdate="10.03.2013" eventtime="13:30"/><Event eventtypeID="1" orgID="4" week="24" matchID="107160" hometeamID="3696" awayteamID="129" placeID="5372" eventdate="10.03.2013" eventtime="13:30"/><Event eventtypeID="1" orgID="4" week="24" matchID="107161" hometeamID="379" awayteamID="4366" placeID="53" eventdate="10.03.2013" eventtime="13:30"/><Event eventtypeID="1" orgID="4" week="25" matchID="107162" hometeamID="3629" awayteamID="3618" placeID="74" eventdate="17.03.2013" eventtime="13:30"/><Event eventtypeID="1" orgID="4" week="25" matchID="107163" hometeamID="3594" awayteamID="3639" placeID="159" eventdate="17.03.2013" eventtime="13:30"/><Event eventtypeID="1" orgID="4" week="25" matchID="107164" hometeamID="30" awayteamID="130" placeID="143" eventdate="17.03.2013" eventtime="13:30"/><Event eventtypeID="1" orgID="4" week="25" matchID="107165" hometeamID="3623" awayteamID="121" placeID="104" eventdate="17.03.2013" eventtime="13:30"/><Event eventtypeID="1" orgID="4" week="25" matchID="107166" hometeamID="3637" awayteamID="379" placeID="154" eventdate="17.03.2013" eventtime="13:30"/><Event eventtypeID="1" orgID="4" week="25" matchID="107167" hometeamID="4366" awayteamID="3696" placeID="20" eventdate="17.03.2013" eventtime="13:30"/><Event eventtypeID="1" orgID="4" week="25" matchID="107168" hometeamID="129" awayteamID="114" placeID="82" eventdate="17.03.2013" eventtime="13:30"/><Event eventtypeID="1" orgID="4" week="25" matchID="107169" hometeamID="3602" awayteamID="58" placeID="96" eventdate="17.03.2013" eventtime="13:30"/><Event eventtypeID="1" orgID="4" week="26" matchID="107170" hometeamID="91" awayteamID="3623" placeID="33" eventdate="23.03.2013" eventtime="13:30"/><Event eventtypeID="1" orgID="4" week="26" matchID="107171" hometeamID="121" awayteamID="30" placeID="3763" eventdate="23.03.2013" eventtime="13:30"/><Event eventtypeID="1" orgID="4" week="26" matchID="107172" hometeamID="130" awayteamID="3594" placeID="36" eventdate="23.03.2013" eventtime="13:30"/><Event eventtypeID="1" orgID="4" week="26" matchID="107173" hometeamID="3639" awayteamID="3629" placeID="39" eventdate="23.03.2013" eventtime="13:30"/><Event eventtypeID="1" orgID="4" week="26" matchID="107174" hometeamID="3618" awayteamID="3602" placeID="95" eventdate="23.03.2013" eventtime="13:30"/><Event eventtypeID="1" orgID="4" week="26" matchID="107175" hometeamID="58" awayteamID="129" placeID="148" eventdate="23.03.2013" eventtime="13:30"/><Event eventtypeID="1" orgID="4" week="26" matchID="107176" hometeamID="114" awayteamID="4366" placeID="476" eventdate="23.03.2013" eventtime="13:30"/><Event eventtypeID="1" orgID="4" week="26" matchID="107177" hometeamID="3696" awayteamID="3637" placeID="5372" eventdate="23.03.2013" eventtime="13:30"/><Event eventtypeID="1" orgID="4" week="27" matchID="107178" hometeamID="129" awayteamID="3618" placeID="82" eventdate="31.03.2013" eventtime="14:30"/><Event eventtypeID="1" orgID="4" week="27" matchID="107179" hometeamID="3602" awayteamID="3639" placeID="96" eventdate="31.03.2013" eventtime="14:30"/><Event eventtypeID="1" orgID="4" week="27" matchID="107180" hometeamID="3629" awayteamID="130" placeID="74" eventdate="31.03.2013" eventtime="14:30"/><Event eventtypeID="1" orgID="4" week="27" matchID="107181" hometeamID="3594" awayteamID="121" placeID="159" eventdate="31.03.2013" eventtime="14:30"/><Event eventtypeID="1" orgID="4" week="27" matchID="107182" hometeamID="30" awayteamID="91" placeID="143" eventdate="31.03.2013" eventtime="14:30"/><Event eventtypeID="1" orgID="4" week="27" matchID="107183" hometeamID="379" awayteamID="3696" placeID="53" eventdate="31.03.2013" eventtime="14:30"/><Event eventtypeID="1" orgID="4" week="27" matchID="107184" hometeamID="3637" awayteamID="114" placeID="154" eventdate="31.03.2013" eventtime="14:30"/><Event eventtypeID="1" orgID="4" week="27" matchID="107185" hometeamID="4366" awayteamID="58" placeID="20" eventdate="31.03.2013" eventtime="14:30"/><Event eventtypeID="1" orgID="4" week="28" matchID="107186" hometeamID="3623" awayteamID="30" placeID="104" eventdate="03.04.2013" eventtime="14:30"/><Event eventtypeID="1" orgID="4" week="28" matchID="107187" hometeamID="91" awayteamID="3594" placeID="33" eventdate="03.04.2013" eventtime="14:30"/><Event eventtypeID="1" orgID="4" week="28" matchID="107188" hometeamID="121" awayteamID="3629" placeID="3763" eventdate="03.04.2013" eventtime="14:30"/><Event eventtypeID="1" orgID="4" week="28" matchID="107189" hometeamID="130" awayteamID="3602" placeID="36" eventdate="03.04.2013" eventtime="14:30"/><Event eventtypeID="1" orgID="4" week="28" matchID="107190" hometeamID="3639" awayteamID="129" placeID="39" eventdate="03.04.2013" eventtime="14:30"/><Event eventtypeID="1" orgID="4" week="28" matchID="107191" hometeamID="3618" awayteamID="4366" placeID="95" eventdate="03.04.2013" eventtime="14:30"/><Event eventtypeID="1" orgID="4" week="28" matchID="107192" hometeamID="58" awayteamID="3637" placeID="148" eventdate="03.04.2013" eventtime="14:30"/><Event eventtypeID="1" orgID="4" week="28" matchID="107193" hometeamID="114" awayteamID="379" placeID="476" eventdate="03.04.2013" eventtime="14:30"/><Event eventtypeID="1" orgID="4" week="29" matchID="107194" hometeamID="3637" awayteamID="3618" placeID="154" eventdate="07.04.2013" eventtime="14:30"/><Event eventtypeID="1" orgID="4" week="29" matchID="107195" hometeamID="4366" awayteamID="3639" placeID="20" eventdate="07.04.2013" eventtime="14:30"/><Event eventtypeID="1" orgID="4" week="29" matchID="107196" hometeamID="129" awayteamID="130" placeID="82" eventdate="07.04.2013" eventtime="14:30"/><Event eventtypeID="1" orgID="4" week="29" matchID="107197" hometeamID="3602" awayteamID="121" placeID="96" eventdate="07.04.2013" eventtime="14:30"/><Event eventtypeID="1" orgID="4" week="29" matchID="107198" hometeamID="3629" awayteamID="91" placeID="74" eventdate="07.04.2013" eventtime="14:30"/><Event eventtypeID="1" orgID="4" week="29" matchID="107199" hometeamID="3594" awayteamID="3623" placeID="159" eventdate="07.04.2013" eventtime="14:30"/><Event eventtypeID="1" orgID="4" week="29" matchID="107200" hometeamID="3696" awayteamID="114" placeID="5372" eventdate="07.04.2013" eventtime="14:30"/><Event eventtypeID="1" orgID="4" week="29" matchID="107201" hometeamID="379" awayteamID="58" placeID="53" eventdate="07.04.2013" eventtime="14:30"/><Event eventtypeID="1" orgID="4" week="30" matchID="107202" hometeamID="30" awayteamID="3594" placeID="143" eventdate="14.04.2013" eventtime="14:30"/><Event eventtypeID="1" orgID="4" week="30" matchID="107203" hometeamID="3623" awayteamID="3629" placeID="104" eventdate="14.04.2013" eventtime="14:30"/><Event eventtypeID="1" orgID="4" week="30" matchID="107204" hometeamID="91" awayteamID="3602" placeID="33" eventdate="14.04.2013" eventtime="14:30"/><Event eventtypeID="1" orgID="4" week="30" matchID="107205" hometeamID="121" awayteamID="129" placeID="3763" eventdate="14.04.2013" eventtime="14:30"/><Event eventtypeID="1" orgID="4" week="30" matchID="107206" hometeamID="130" awayteamID="4366" placeID="36" eventdate="14.04.2013" eventtime="14:30"/><Event eventtypeID="1" orgID="4" week="30" matchID="107207" hometeamID="3639" awayteamID="3637" placeID="39" eventdate="14.04.2013" eventtime="14:30"/><Event eventtypeID="1" orgID="4" week="30" matchID="107208" hometeamID="3618" awayteamID="379" placeID="95" eventdate="14.04.2013" eventtime="14:30"/><Event eventtypeID="1" orgID="4" week="30" matchID="107209" hometeamID="58" awayteamID="3696" placeID="148" eventdate="14.04.2013" eventtime="14:30"/><Event eventtypeID="1" orgID="4" week="31" matchID="107210" hometeamID="3696" awayteamID="3618" placeID="5372" eventdate="21.04.2013" eventtime="14:30"/><Event eventtypeID="1" orgID="4" week="31" matchID="107211" hometeamID="379" awayteamID="3639" placeID="53" eventdate="21.04.2013" eventtime="14:30"/><Event eventtypeID="1" orgID="4" week="31" matchID="107212" hometeamID="3637" awayteamID="130" placeID="154" eventdate="21.04.2013" eventtime="14:30"/><Event eventtypeID="1" orgID="4" week="31" matchID="107213" hometeamID="4366" awayteamID="121" placeID="20" eventdate="21.04.2013" eventtime="14:30"/><Event eventtypeID="1" orgID="4" week="31" matchID="107214" hometeamID="129" awayteamID="91" placeID="82" eventdate="21.04.2013" eventtime="14:30"/><Event eventtypeID="1" orgID="4" week="31" matchID="107215" hometeamID="3602" awayteamID="3623" placeID="96" eventdate="21.04.2013" eventtime="14:30"/><Event eventtypeID="1" orgID="4" week="31" matchID="107216" hometeamID="3629" awayteamID="30" placeID="74" eventdate="21.04.2013" eventtime="14:30"/><Event eventtypeID="1" orgID="4" week="31" matchID="107217" hometeamID="114" awayteamID="58" placeID="476" eventdate="21.04.2013" eventtime="14:30"/><Event eventtypeID="1" orgID="4" week="32" matchID="107218" hometeamID="3594" awayteamID="3629" placeID="159" eventdate="28.04.2013" eventtime="15:30"/><Event eventtypeID="1" orgID="4" week="32" matchID="107219" hometeamID="30" awayteamID="3602" placeID="143" eventdate="28.04.2013" eventtime="15:30"/><Event eventtypeID="1" orgID="4" week="32" matchID="107220" hometeamID="3623" awayteamID="129" placeID="104" eventdate="28.04.2013" eventtime="15:30"/><Event eventtypeID="1" orgID="4" week="32" matchID="107221" hometeamID="91" awayteamID="4366" placeID="33" eventdate="28.04.2013" eventtime="15:30"/><Event eventtypeID="1" orgID="4" week="32" matchID="107222" hometeamID="121" awayteamID="3637" placeID="3763" eventdate="28.04.2013" eventtime="15:30"/><Event eventtypeID="1" orgID="4" week="32" matchID="107223" hometeamID="130" awayteamID="379" placeID="36" eventdate="28.04.2013" eventtime="15:30"/><Event eventtypeID="1" orgID="4" week="32" matchID="107224" hometeamID="3639" awayteamID="3696" placeID="39" eventdate="28.04.2013" eventtime="15:30"/><Event eventtypeID="1" orgID="4" week="32" matchID="107225" hometeamID="3618" awayteamID="114" placeID="95" eventdate="28.04.2013" eventtime="15:30"/><Event eventtypeID="1" orgID="4" week="33" matchID="107226" hometeamID="58" awayteamID="3618" placeID="148" eventdate="05.05.2013" eventtime="15:30"/><Event eventtypeID="1" orgID="4" week="33" matchID="107227" hometeamID="114" awayteamID="3639" placeID="476" eventdate="05.05.2013" eventtime="15:30"/><Event eventtypeID="1" orgID="4" week="33" matchID="107228" hometeamID="3696" awayteamID="130" placeID="5372" eventdate="05.05.2013" eventtime="15:30"/><Event eventtypeID="1" orgID="4" week="33" matchID="107229" hometeamID="379" awayteamID="121" placeID="53" eventdate="05.05.2013" eventtime="15:30"/><Event eventtypeID="1" orgID="4" week="33" matchID="107230" hometeamID="3637" awayteamID="91" placeID="154" eventdate="05.05.2013" eventtime="15:30"/><Event eventtypeID="1" orgID="4" week="33" matchID="107231" hometeamID="4366" awayteamID="3623" placeID="20" eventdate="05.05.2013" eventtime="15:30"/><Event eventtypeID="1" orgID="4" week="33" matchID="107232" hometeamID="129" awayteamID="30" placeID="82" eventdate="05.05.2013" eventtime="15:30"/><Event eventtypeID="1" orgID="4" week="33" matchID="107233" hometeamID="3602" awayteamID="3594" placeID="96" eventdate="05.05.2013" eventtime="15:30"/><Event eventtypeID="1" orgID="4" week="34" matchID="107234" hometeamID="3629" awayteamID="3602" placeID="74" eventdate="12.05.2013" eventtime="15:30"/><Event eventtypeID="1" orgID="4" week="34" matchID="107235" hometeamID="3594" awayteamID="129" placeID="159" eventdate="12.05.2013" eventtime="15:30"/><Event eventtypeID="1" orgID="4" week="34" matchID="107236" hometeamID="30" awayteamID="4366" placeID="143" eventdate="12.05.2013" eventtime="15:30"/><Event eventtypeID="1" orgID="4" week="34" matchID="107237" hometeamID="3623" awayteamID="3637" placeID="104" eventdate="12.05.2013" eventtime="15:30"/><Event eventtypeID="1" orgID="4" week="34" matchID="107238" hometeamID="91" awayteamID="379" placeID="33" eventdate="12.05.2013" eventtime="15:30"/><Event eventtypeID="1" orgID="4" week="34" matchID="107239" hometeamID="121" awayteamID="3696" placeID="3763" eventdate="12.05.2013" eventtime="15:30"/><Event eventtypeID="1" orgID="4" week="34" matchID="107240" hometeamID="130" awayteamID="114" placeID="36" eventdate="12.05.2013" eventtime="15:30"/><Event eventtypeID="1" orgID="4" week="34" matchID="107241" hometeamID="3639" awayteamID="58" placeID="39" eventdate="12.05.2013" eventtime="15:30"/></Events>