<?xml version="1.0" encoding="ISO-8859-9"?> <Events org="tffbirincilig"><Event eventtypeID="1" orgID="6" week="1" matchID="107820" hometeamID="4255" awayteamID="1211" placeID="618" eventdate="08.09.2012" eventtime="16:00"/><Event eventtypeID="1" orgID="6" week="1" matchID="107825" hometeamID="2035" awayteamID="1075" placeID="64" eventdate="09.09.2012" eventtime="15:00"/><Event eventtypeID="1" orgID="6" week="1" matchID="107826" hometeamID="1120" awayteamID="3616" placeID="363" eventdate="09.09.2012" eventtime="16:00"/><Event eventtypeID="1" orgID="6" week="1" matchID="107827" hometeamID="5025" awayteamID="34" placeID="171" eventdate="09.09.2012" eventtime="16:00"/><Event eventtypeID="1" orgID="6" week="1" matchID="107828" hometeamID="3089" awayteamID="32" placeID="40" eventdate="09.09.2012" eventtime="16:00"/><Event eventtypeID="1" orgID="6" week="1" matchID="107821" hometeamID="102" awayteamID="44" placeID="1617" eventdate="09.09.2012" eventtime="16:00"/><Event eventtypeID="1" orgID="6" week="1" matchID="107822" hometeamID="137" awayteamID="3292" placeID="52" eventdate="09.09.2012" eventtime="16:00"/><Event eventtypeID="1" orgID="6" week="1" matchID="107823" hometeamID="1343" awayteamID="3661" placeID="4911" eventdate="09.09.2012" eventtime="16:00"/><Event eventtypeID="1" orgID="6" week="1" matchID="107824" hometeamID="742" awayteamID="3636" placeID="5353" eventdate="09.09.2012" eventtime="16:00"/><Event eventtypeID="1" orgID="6" week="2" matchID="107836" hometeamID="3636" awayteamID="137" placeID="175" eventdate="15.09.2012" eventtime="16:00"/><Event eventtypeID="1" orgID="6" week="2" matchID="107837" hometeamID="32" awayteamID="5025" placeID="5" eventdate="16.09.2012" eventtime="16:00"/><Event eventtypeID="1" orgID="6" week="2" matchID="107829" hometeamID="44" awayteamID="1343" placeID="405" eventdate="16.09.2012" eventtime="16:00"/><Event eventtypeID="1" orgID="6" week="2" matchID="107830" hometeamID="34" awayteamID="1120" placeID="195" eventdate="16.09.2012" eventtime="16:00"/><Event eventtypeID="1" orgID="6" week="2" matchID="107831" hometeamID="3616" awayteamID="2035" placeID="130" eventdate="16.09.2012" eventtime="16:00"/><Event eventtypeID="1" orgID="6" week="2" matchID="107832" hometeamID="1075" awayteamID="742" placeID="34" eventdate="16.09.2012" eventtime="16:00"/><Event eventtypeID="1" orgID="6" week="2" matchID="107833" hometeamID="3292" awayteamID="102" placeID="4875" eventdate="16.09.2012" eventtime="16:00"/><Event eventtypeID="1" orgID="6" week="2" matchID="107834" hometeamID="3661" awayteamID="4255" placeID="437" eventdate="16.09.2012" eventtime="16:00"/><Event eventtypeID="1" orgID="6" week="2" matchID="107835" hometeamID="1211" awayteamID="3089" placeID="3750" eventdate="16.09.2012" eventtime="16:00"/><Event eventtypeID="1" orgID="6" week="3" matchID="107838" hometeamID="3089" awayteamID="5025" placeID="40" eventdate="23.09.2012" eventtime="15:00"/><Event eventtypeID="1" orgID="6" week="3" matchID="107839" hometeamID="1343" awayteamID="3292" placeID="4911" eventdate="23.09.2012" eventtime="15:00"/><Event eventtypeID="1" orgID="6" week="3" matchID="107840" hometeamID="742" awayteamID="3616" placeID="5353" eventdate="23.09.2012" eventtime="15:00"/><Event eventtypeID="1" orgID="6" week="3" matchID="107841" hometeamID="4255" awayteamID="44" placeID="79" eventdate="23.09.2012" eventtime="15:00"/><Event eventtypeID="1" orgID="6" week="3" matchID="107842" hometeamID="102" awayteamID="3636" placeID="1617" eventdate="23.09.2012" eventtime="15:00"/><Event eventtypeID="1" orgID="6" week="3" matchID="107843" hometeamID="137" awayteamID="1075" placeID="52" eventdate="23.09.2012" eventtime="15:00"/><Event eventtypeID="1" orgID="6" week="3" matchID="107844" hometeamID="1120" awayteamID="32" placeID="363" eventdate="23.09.2012" eventtime="15:00"/><Event eventtypeID="1" orgID="6" week="3" matchID="107845" hometeamID="1211" awayteamID="3661" placeID="3750" eventdate="23.09.2012" eventtime="15:00"/><Event eventtypeID="1" orgID="6" week="3" matchID="107846" hometeamID="2035" awayteamID="34" placeID="64" eventdate="23.09.2012" eventtime="15:00"/><Event eventtypeID="1" orgID="6" week="4" matchID="107847" hometeamID="1075" awayteamID="102" placeID="34" eventdate="30.09.2012" eventtime="15:00"/><Event eventtypeID="1" orgID="6" week="4" matchID="107848" hometeamID="3292" awayteamID="4255" placeID="4875" eventdate="30.09.2012" eventtime="15:00"/><Event eventtypeID="1" orgID="6" week="4" matchID="107849" hometeamID="5025" awayteamID="1120" placeID="171" eventdate="30.09.2012" eventtime="15:00"/><Event eventtypeID="1" orgID="6" week="4" matchID="107850" hometeamID="3616" awayteamID="137" placeID="130" eventdate="30.09.2012" eventtime="15:00"/><Event eventtypeID="1" orgID="6" week="4" matchID="107852" hometeamID="44" awayteamID="1211" placeID="405" eventdate="30.09.2012" eventtime="15:00"/><Event eventtypeID="1" orgID="6" week="4" matchID="107853" hometeamID="3661" awayteamID="3089" placeID="437" eventdate="30.09.2012" eventtime="15:00"/><Event eventtypeID="1" orgID="6" week="4" matchID="107854" hometeamID="34" awayteamID="742" placeID="195" eventdate="30.09.2012" eventtime="15:00"/><Event eventtypeID="1" orgID="6" week="4" matchID="107855" hometeamID="32" awayteamID="2035" placeID="5" eventdate="30.09.2012" eventtime="15:00"/><Event eventtypeID="1" orgID="6" week="4" matchID="107851" hometeamID="3636" awayteamID="1343" placeID="175" eventdate="01.10.2012" eventtime="15:00"/><Event eventtypeID="1" orgID="6" week="5" matchID="107856" hometeamID="4255" awayteamID="3636" placeID="79" eventdate="07.10.2012" eventtime="15:00"/><Event eventtypeID="1" orgID="6" week="5" matchID="107857" hometeamID="3661" awayteamID="44" placeID="437" eventdate="07.10.2012" eventtime="15:00"/><Event eventtypeID="1" orgID="6" week="5" matchID="107858" hometeamID="1211" awayteamID="3292" placeID="3750" eventdate="07.10.2012" eventtime="15:00"/><Event eventtypeID="1" orgID="6" week="5" matchID="107859" hometeamID="3089" awayteamID="1120" placeID="40" eventdate="07.10.2012" eventtime="15:00"/><Event eventtypeID="1" orgID="6" week="5" matchID="107860" hometeamID="1343" awayteamID="1075" placeID="4911" eventdate="07.10.2012" eventtime="15:00"/><Event eventtypeID="1" orgID="6" week="5" matchID="107861" hometeamID="102" awayteamID="3616" placeID="1617" eventdate="07.10.2012" eventtime="15:00"/><Event eventtypeID="1" orgID="6" week="5" matchID="107862" hometeamID="137" awayteamID="34" placeID="52" eventdate="07.10.2012" eventtime="15:00"/><Event eventtypeID="1" orgID="6" week="5" matchID="107863" hometeamID="742" awayteamID="32" placeID="5353" eventdate="07.10.2012" eventtime="15:00"/><Event eventtypeID="1" orgID="6" week="5" matchID="107864" hometeamID="2035" awayteamID="5025" placeID="64" eventdate="07.10.2012" eventtime="15:00"/><Event eventtypeID="1" orgID="6" week="6" matchID="107871" hometeamID="1120" awayteamID="2035" placeID="363" eventdate="14.10.2012" eventtime="14:00"/><Event eventtypeID="1" orgID="6" week="6" matchID="107872" hometeamID="5025" awayteamID="742" placeID="171" eventdate="14.10.2012" eventtime="15:00"/><Event eventtypeID="1" orgID="6" week="6" matchID="107873" hometeamID="34" awayteamID="102" placeID="195" eventdate="14.10.2012" eventtime="15:00"/><Event eventtypeID="1" orgID="6" week="6" matchID="107865" hometeamID="3292" awayteamID="3661" placeID="4875" eventdate="14.10.2012" eventtime="15:00"/><Event eventtypeID="1" orgID="6" week="6" matchID="107866" hometeamID="44" awayteamID="3089" placeID="405" eventdate="14.10.2012" eventtime="15:00"/><Event eventtypeID="1" orgID="6" week="6" matchID="107867" hometeamID="32" awayteamID="137" placeID="5" eventdate="14.10.2012" eventtime="15:00"/><Event eventtypeID="1" orgID="6" week="6" matchID="107868" hometeamID="3616" awayteamID="1343" placeID="130" eventdate="14.10.2012" eventtime="15:00"/><Event eventtypeID="1" orgID="6" week="6" matchID="107869" hometeamID="1075" awayteamID="4255" placeID="34" eventdate="14.10.2012" eventtime="15:00"/><Event eventtypeID="1" orgID="6" week="6" matchID="107870" hometeamID="3636" awayteamID="1211" placeID="175" eventdate="14.10.2012" eventtime="15:00"/><Event eventtypeID="1" orgID="6" week="7" matchID="107874" hometeamID="4255" awayteamID="3616" placeID="79" eventdate="21.10.2012" eventtime="15:00"/><Event eventtypeID="1" orgID="6" week="7" matchID="107875" hometeamID="137" awayteamID="5025" placeID="52" eventdate="21.10.2012" eventtime="15:00"/><Event eventtypeID="1" orgID="6" week="7" matchID="107876" hometeamID="44" awayteamID="3292" placeID="405" eventdate="21.10.2012" eventtime="15:00"/><Event eventtypeID="1" orgID="6" week="7" matchID="107877" hometeamID="1343" awayteamID="34" placeID="4911" eventdate="21.10.2012" eventtime="15:00"/><Event eventtypeID="1" orgID="6" week="7" matchID="107878" hometeamID="102" awayteamID="32" placeID="1617" eventdate="21.10.2012" eventtime="15:00"/><Event eventtypeID="1" orgID="6" week="7" matchID="107879" hometeamID="742" awayteamID="1120" placeID="5353" eventdate="21.10.2012" eventtime="15:00"/><Event eventtypeID="1" orgID="6" week="7" matchID="107880" hometeamID="3661" awayteamID="3636" placeID="437" eventdate="21.10.2012" eventtime="15:00"/><Event eventtypeID="1" orgID="6" week="7" matchID="107881" hometeamID="1211" awayteamID="1075" placeID="3750" eventdate="21.10.2012" eventtime="15:00"/><Event eventtypeID="1" orgID="6" week="7" matchID="107882" hometeamID="3089" awayteamID="2035" placeID="40" eventdate="21.10.2012" eventtime="15:00"/><Event eventtypeID="1" orgID="6" week="8" matchID="107883" hometeamID="32" awayteamID="1343" placeID="5" eventdate="24.10.2012" eventtime="15:00"/><Event eventtypeID="1" orgID="6" week="8" matchID="107884" hometeamID="1075" awayteamID="3661" placeID="34" eventdate="24.10.2012" eventtime="15:00"/><Event eventtypeID="1" orgID="6" week="8" matchID="107885" hometeamID="5025" awayteamID="102" placeID="5363" eventdate="24.10.2012" eventtime="15:00"/><Event eventtypeID="1" orgID="6" week="8" matchID="107887" hometeamID="3636" awayteamID="44" placeID="175" eventdate="24.10.2012" eventtime="15:00"/><Event eventtypeID="1" orgID="6" week="8" matchID="107888" hometeamID="3292" awayteamID="3089" placeID="4875" eventdate="24.10.2012" eventtime="15:00"/><Event eventtypeID="1" orgID="6" week="8" matchID="107889" hometeamID="2035" awayteamID="742" placeID="64" eventdate="24.10.2012" eventtime="15:00"/><Event eventtypeID="1" orgID="6" week="8" matchID="107890" hometeamID="1120" awayteamID="137" placeID="363" eventdate="24.10.2012" eventtime="15:00"/><Event eventtypeID="1" orgID="6" week="8" matchID="107891" hometeamID="34" awayteamID="4255" placeID="195" eventdate="24.10.2012" eventtime="15:00"/><Event eventtypeID="1" orgID="6" week="8" matchID="107886" hometeamID="3616" awayteamID="1211" placeID="130" eventdate="24.10.2012" eventtime="15:02"/><Event eventtypeID="1" orgID="6" week="9" matchID="107895" hometeamID="4255" awayteamID="32" placeID="79" eventdate="27.10.2012" eventtime="13:30"/><Event eventtypeID="1" orgID="6" week="9" matchID="107896" hometeamID="1343" awayteamID="5025" placeID="4911" eventdate="28.10.2012" eventtime="13:30"/><Event eventtypeID="1" orgID="6" week="9" matchID="107897" hometeamID="137" awayteamID="2035" placeID="52" eventdate="28.10.2012" eventtime="13:30"/><Event eventtypeID="1" orgID="6" week="9" matchID="107898" hometeamID="44" awayteamID="1075" placeID="405" eventdate="28.10.2012" eventtime="13:30"/><Event eventtypeID="1" orgID="6" week="9" matchID="107899" hometeamID="3661" awayteamID="3616" placeID="437" eventdate="28.10.2012" eventtime="13:30"/><Event eventtypeID="1" orgID="6" week="9" matchID="107900" hometeamID="3089" awayteamID="742" placeID="40" eventdate="28.10.2012" eventtime="13:30"/><Event eventtypeID="1" orgID="6" week="9" matchID="107892" hometeamID="102" awayteamID="1120" placeID="1617" eventdate="28.10.2012" eventtime="13:30"/><Event eventtypeID="1" orgID="6" week="9" matchID="107893" hometeamID="3292" awayteamID="3636" placeID="4875" eventdate="28.10.2012" eventtime="13:30"/><Event eventtypeID="1" orgID="6" week="9" matchID="107894" hometeamID="1211" awayteamID="34" placeID="3750" eventdate="28.10.2012" eventtime="13:30"/><Event eventtypeID="1" orgID="6" week="10" matchID="107901" hometeamID="1120" awayteamID="1343" placeID="363" eventdate="04.11.2012" eventtime="13:30"/><Event eventtypeID="1" orgID="6" week="10" matchID="107902" hometeamID="34" awayteamID="3661" placeID="195" eventdate="04.11.2012" eventtime="13:30"/><Event eventtypeID="1" orgID="6" week="10" matchID="107903" hometeamID="32" awayteamID="1211" placeID="5" eventdate="04.11.2012" eventtime="13:30"/><Event eventtypeID="1" orgID="6" week="10" matchID="107904" hometeamID="3616" awayteamID="44" placeID="130" eventdate="04.11.2012" eventtime="13:30"/><Event eventtypeID="1" orgID="6" week="10" matchID="107905" hometeamID="1075" awayteamID="3292" placeID="34" eventdate="04.11.2012" eventtime="13:30"/><Event eventtypeID="1" orgID="6" week="10" matchID="107906" hometeamID="3636" awayteamID="3089" placeID="175" eventdate="04.11.2012" eventtime="13:30"/><Event eventtypeID="1" orgID="6" week="10" matchID="107907" hometeamID="742" awayteamID="137" placeID="5353" eventdate="04.11.2012" eventtime="13:30"/><Event eventtypeID="1" orgID="6" week="10" matchID="107908" hometeamID="2035" awayteamID="102" placeID="64" eventdate="04.11.2012" eventtime="13:30"/><Event eventtypeID="1" orgID="6" week="10" matchID="107909" hometeamID="5025" awayteamID="4255" placeID="5363" eventdate="04.11.2012" eventtime="13:30"/><Event eventtypeID="1" orgID="6" week="11" matchID="107913" hometeamID="4255" awayteamID="1120" placeID="618" eventdate="10.11.2012" eventtime="13:30"/><Event eventtypeID="1" orgID="6" week="11" matchID="107914" hometeamID="1343" awayteamID="2035" placeID="4911" eventdate="11.11.2012" eventtime="13:30"/><Event eventtypeID="1" orgID="6" week="11" matchID="107915" hometeamID="102" awayteamID="742" placeID="1617" eventdate="11.11.2012" eventtime="13:30"/><Event eventtypeID="1" orgID="6" week="11" matchID="107916" hometeamID="3636" awayteamID="1075" placeID="175" eventdate="11.11.2012" eventtime="13:30"/><Event eventtypeID="1" orgID="6" week="11" matchID="107917" hometeamID="3661" awayteamID="32" placeID="437" eventdate="11.11.2012" eventtime="13:30"/><Event eventtypeID="1" orgID="6" week="11" matchID="107918" hometeamID="1211" awayteamID="5025" placeID="3750" eventdate="11.11.2012" eventtime="13:30"/><Event eventtypeID="1" orgID="6" week="11" matchID="107910" hometeamID="3292" awayteamID="3616" placeID="4875" eventdate="11.11.2012" eventtime="13:30"/><Event eventtypeID="1" orgID="6" week="11" matchID="107911" hometeamID="44" awayteamID="34" placeID="405" eventdate="11.11.2012" eventtime="13:30"/><Event eventtypeID="1" orgID="6" week="11" matchID="107912" hometeamID="3089" awayteamID="137" placeID="40" eventdate="11.11.2012" eventtime="13:30"/><Event eventtypeID="1" orgID="6" week="12" matchID="107919" hometeamID="742" awayteamID="1343" placeID="5353" eventdate="18.11.2012" eventtime="13:30"/><Event eventtypeID="1" orgID="6" week="12" matchID="107920" hometeamID="1120" awayteamID="1211" placeID="363" eventdate="18.11.2012" eventtime="13:30"/><Event eventtypeID="1" orgID="6" week="12" matchID="107921" hometeamID="34" awayteamID="3292" placeID="195" eventdate="18.11.2012" eventtime="13:30"/><Event eventtypeID="1" orgID="6" week="12" matchID="107922" hometeamID="32" awayteamID="44" placeID="5" eventdate="18.11.2012" eventtime="13:30"/><Event eventtypeID="1" orgID="6" week="12" matchID="107923" hometeamID="3616" awayteamID="3636" placeID="130" eventdate="18.11.2012" eventtime="13:30"/><Event eventtypeID="1" orgID="6" week="12" matchID="107924" hometeamID="1075" awayteamID="3089" placeID="34" eventdate="18.11.2012" eventtime="13:30"/><Event eventtypeID="1" orgID="6" week="12" matchID="107925" hometeamID="137" awayteamID="102" placeID="52" eventdate="18.11.2012" eventtime="13:30"/><Event eventtypeID="1" orgID="6" week="12" matchID="107926" hometeamID="2035" awayteamID="4255" placeID="64" eventdate="18.11.2012" eventtime="13:30"/><Event eventtypeID="1" orgID="6" week="12" matchID="107927" hometeamID="5025" awayteamID="3661" placeID="5363" eventdate="18.11.2012" eventtime="13:30"/><Event eventtypeID="1" orgID="6" week="13" matchID="107928" hometeamID="4255" awayteamID="742" placeID="618" eventdate="25.11.2012" eventtime="13:30"/><Event eventtypeID="1" orgID="6" week="13" matchID="107929" hometeamID="44" awayteamID="5025" placeID="405" eventdate="25.11.2012" eventtime="13:30"/><Event eventtypeID="1" orgID="6" week="13" matchID="107930" hometeamID="3661" awayteamID="1120" placeID="437" eventdate="25.11.2012" eventtime="13:30"/><Event eventtypeID="1" orgID="6" week="13" matchID="107931" hometeamID="1343" awayteamID="137" placeID="4911" eventdate="25.11.2012" eventtime="13:30"/><Event eventtypeID="1" orgID="6" week="13" matchID="107932" hometeamID="1075" awayteamID="3616" placeID="34" eventdate="25.11.2012" eventtime="13:30"/><Event eventtypeID="1" orgID="6" week="13" matchID="107933" hometeamID="3636" awayteamID="34" placeID="175" eventdate="25.11.2012" eventtime="13:30"/><Event eventtypeID="1" orgID="6" week="13" matchID="107934" hometeamID="3292" awayteamID="32" placeID="4875" eventdate="25.11.2012" eventtime="13:30"/><Event eventtypeID="1" orgID="6" week="13" matchID="107935" hometeamID="1211" awayteamID="2035" placeID="3750" eventdate="25.11.2012" eventtime="13:30"/><Event eventtypeID="1" orgID="6" week="13" matchID="107936" hometeamID="3089" awayteamID="102" placeID="40" eventdate="25.11.2012" eventtime="13:30"/><Event eventtypeID="1" orgID="6" week="14" matchID="107939" hometeamID="34" awayteamID="1075" placeID="195" eventdate="02.12.2012" eventtime="12:30"/><Event eventtypeID="1" orgID="6" week="14" matchID="107940" hometeamID="32" awayteamID="3636" placeID="5" eventdate="02.12.2012" eventtime="13:30"/><Event eventtypeID="1" orgID="6" week="14" matchID="107941" hometeamID="3616" awayteamID="3089" placeID="130" eventdate="02.12.2012" eventtime="13:30"/><Event eventtypeID="1" orgID="6" week="14" matchID="107942" hometeamID="742" awayteamID="1211" placeID="5353" eventdate="02.12.2012" eventtime="13:30"/><Event eventtypeID="1" orgID="6" week="14" matchID="107943" hometeamID="2035" awayteamID="3661" placeID="64" eventdate="02.12.2012" eventtime="13:30"/><Event eventtypeID="1" orgID="6" week="14" matchID="107944" hometeamID="1120" awayteamID="44" placeID="363" eventdate="02.12.2012" eventtime="13:30"/><Event eventtypeID="1" orgID="6" week="14" matchID="107945" hometeamID="5025" awayteamID="3292" placeID="5363" eventdate="02.12.2012" eventtime="13:30"/><Event eventtypeID="1" orgID="6" week="14" matchID="107937" hometeamID="102" awayteamID="1343" placeID="1617" eventdate="02.12.2012" eventtime="13:30"/><Event eventtypeID="1" orgID="6" week="14" matchID="107938" hometeamID="137" awayteamID="4255" placeID="52" eventdate="02.12.2012" eventtime="13:30"/><Event eventtypeID="1" orgID="6" week="15" matchID="107954" hometeamID="34" awayteamID="3616" placeID="195" eventdate="09.12.2012" eventtime="12:30"/><Event eventtypeID="1" orgID="6" week="15" matchID="107946" hometeamID="4255" awayteamID="102" placeID="79" eventdate="09.12.2012" eventtime="13:30"/><Event eventtypeID="1" orgID="6" week="15" matchID="107947" hometeamID="3636" awayteamID="5025" placeID="175" eventdate="09.12.2012" eventtime="13:30"/><Event eventtypeID="1" orgID="6" week="15" matchID="107948" hometeamID="3661" awayteamID="742" placeID="437" eventdate="09.12.2012" eventtime="13:30"/><Event eventtypeID="1" orgID="6" week="15" matchID="107949" hometeamID="1343" awayteamID="3089" placeID="4911" eventdate="09.12.2012" eventtime="13:30"/><Event eventtypeID="1" orgID="6" week="15" matchID="107950" hometeamID="1075" awayteamID="32" placeID="34" eventdate="09.12.2012" eventtime="13:30"/><Event eventtypeID="1" orgID="6" week="15" matchID="107951" hometeamID="3292" awayteamID="1120" placeID="4875" eventdate="09.12.2012" eventtime="13:30"/><Event eventtypeID="1" orgID="6" week="15" matchID="107952" hometeamID="44" awayteamID="2035" placeID="405" eventdate="09.12.2012" eventtime="13:30"/><Event eventtypeID="1" orgID="6" week="15" matchID="107953" hometeamID="1211" awayteamID="137" placeID="3750" eventdate="09.12.2012" eventtime="13:30"/><Event eventtypeID="1" orgID="6" week="16" matchID="107957" hometeamID="3089" awayteamID="34" placeID="40" eventdate="16.12.2012" eventtime="12:30"/><Event eventtypeID="1" orgID="6" week="16" matchID="107958" hometeamID="32" awayteamID="3616" placeID="5" eventdate="16.12.2012" eventtime="13:30"/><Event eventtypeID="1" orgID="6" week="16" matchID="107959" hometeamID="1343" awayteamID="4255" placeID="4911" eventdate="16.12.2012" eventtime="13:30"/><Event eventtypeID="1" orgID="6" week="16" matchID="107960" hometeamID="102" awayteamID="1211" placeID="1617" eventdate="16.12.2012" eventtime="13:30"/><Event eventtypeID="1" orgID="6" week="16" matchID="107961" hometeamID="742" awayteamID="44" placeID="5353" eventdate="16.12.2012" eventtime="13:30"/><Event eventtypeID="1" orgID="6" week="16" matchID="107962" hometeamID="2035" awayteamID="3292" placeID="64" eventdate="16.12.2012" eventtime="13:30"/><Event eventtypeID="1" orgID="6" week="16" matchID="107963" hometeamID="5025" awayteamID="1075" placeID="5363" eventdate="16.12.2012" eventtime="13:30"/><Event eventtypeID="1" orgID="6" week="16" matchID="107955" hometeamID="137" awayteamID="3661" placeID="52" eventdate="16.12.2012" eventtime="13:30"/><Event eventtypeID="1" orgID="6" week="16" matchID="107956" hometeamID="1120" awayteamID="3636" placeID="363" eventdate="16.12.2012" eventtime="13:30"/><Event eventtypeID="1" orgID="6" week="17" matchID="107968" hometeamID="1075" awayteamID="1120" placeID="34" eventdate="22.12.2012" eventtime="13:30"/><Event eventtypeID="1" orgID="6" week="17" matchID="107969" hometeamID="3636" awayteamID="2035" placeID="175" eventdate="22.12.2012" eventtime="13:30"/><Event eventtypeID="1" orgID="6" week="17" matchID="107972" hometeamID="34" awayteamID="32" placeID="195" eventdate="23.12.2012" eventtime="12:30"/><Event eventtypeID="1" orgID="6" week="17" matchID="107970" hometeamID="44" awayteamID="137" placeID="405" eventdate="23.12.2012" eventtime="13:30"/><Event eventtypeID="1" orgID="6" week="17" matchID="107971" hometeamID="3661" awayteamID="102" placeID="437" eventdate="23.12.2012" eventtime="13:30"/><Event eventtypeID="1" orgID="6" week="17" matchID="107964" hometeamID="4255" awayteamID="3089" placeID="79" eventdate="23.12.2012" eventtime="13:30"/><Event eventtypeID="1" orgID="6" week="17" matchID="107965" hometeamID="3292" awayteamID="742" placeID="4875" eventdate="23.12.2012" eventtime="13:30"/><Event eventtypeID="1" orgID="6" week="17" matchID="107966" hometeamID="1211" awayteamID="1343" placeID="3750" eventdate="23.12.2012" eventtime="13:30"/><Event eventtypeID="1" orgID="6" week="17" matchID="107967" hometeamID="3616" awayteamID="5025" placeID="127" eventdate="23.12.2012" eventtime="13:30"/></Events>